packet/_init_.py
packet/function.py
packetForLab2-0.1.dist-info/METADATA
packetForLab2-0.1.dist-info/WHEEL
packetForLab2-0.1.dist-info/top_level.txt
packetForLab2-0.1.dist-info/RECORD
